{
    "description": null,
    "enabled": true,
    "entry_point": "src/wrapper.py",
    "name": "server.group.create",
    "parameters": {
        "base": {
            "default": "server group create",
            "immutable": true,
            "type": "string"
        },
        "cloud": {
            "description": "A specific cloud to query",
            "type": "string"
        },
        "ep": {
            "default": "EntryPoint.parse('server_group_create = openstackclient.compute.v2.server_group:CreateServerGroup')",
            "immutable": true,
            "type": "string"
        },
        "format": {
            "default": "json",
            "description": "the output format, defaults to table (choices: json, shell, table, value, yaml)",
            "type": "string"
        },
        "name": {
            "description": "New server group name",
            "required": true,
            "type": "string"
        },
        "noindent": {
            "default": false,
            "description": "whether to disable indenting the JSON",
            "type": "boolean"
        },
        "policy": {
            "default": "affinity",
            "description": "Add a policy to <name> ('affinity' or 'anti-affinity', default to 'affinity') (choices: affinity, anti-affinity)",
            "type": "string"
        },
        "project_id": {
            "description": "Run the action under a different project, identified by id",
            "type": "string"
        },
        "project_name": {
            "description": "Run the action under a different project, identified by name",
            "type": "string"
        }
    },
    "runner_type": "python-script"
}
