{
    "description": "read the specified Node",
    "enabled": true,
    "entry_point": "readCoreV1Node.py",
    "name": "readCoreV1Node",
    "pack": "kubernetes",
    "parameters": {
        "config_override": {
            "description": "override stackstorm config",
            "type": "object"
        },
        "exact": {
            "description": "Should the export be exact.  Exact export maintains cluster-specific fields like 'Namespace'",
            "type": "boolean"
        },
        "export": {
            "description": "Should this value be exported.  Export strips fields that a user can not specify.",
            "type": "boolean"
        },
        "name": {
            "description": "name of the Node",
            "required": true,
            "type": "string"
        },
        "pretty": {
            "description": "If 'true', then the output is pretty printed.",
            "type": "string"
        }
    },
    "runner_type": "python-script"
}
