{
    "api_url": {
        "description": "Salt NetAPI URL if using remote server",
        "required": false,
        "secret": false,
        "type": "string"
    },
    "eauth": {
        "default": "pam",
        "description": "Salt External Authentication System",
        "required": false,
        "secret": false,
        "type": "string"
    },
    "password": {
        "description": "Password for Salt NetAPI integration",
        "required": false,
        "secret": true,
        "type": "string"
    },
    "username": {
        "description": "Username for Salt NetAPI integration",
        "required": false,
        "secret": false,
        "type": "string"
    },
    "verify_ssl": {
        "default": true,
        "description": "Whether ST2 should verify the Salt NetAPI SSL certificate or not",
        "required": false,
        "secret": false,
        "type": "boolean"
    }
}
