{
    "description": "Create an External network from VSphere port groups",
    "enabled": true,
    "entry_point": "create_ext_network.py",
    "name": "create_ext_network",
    "parameters": {
        "data": {
            "description": "Data structure for new networks",
            "position": 1,
            "required": true,
            "type": "object"
        },
        "vcloud": {
            "description": "Which vcloud to connect to",
            "position": 0,
            "required": false,
            "type": "string"
        }
    },
    "runner_type": "python-script"
}
